vitalx/vitalx/__init__.py
vitalx-0.3.0.dist-info/WHEEL
vitalx-0.3.0.dist-info/METADATA
vitalx-0.3.0.dist-info/RECORD
